Metadata-Version: 2.1
Name: vaby-models-cvr
Version: 0.0.2.post15
Summary: VABY forward models for CVR
Home-page: UNKNOWN
Author: Martin Craig
Author-email: martin.craig@nottingham.ac.uk
License: APACHE-2. See LICENSE file for more details
Platform: UNKNOWN
License-File: LICENSE
